pytest_profiling.py
pytest_profiling-1.8.1.dist-info/LICENSE
pytest_profiling-1.8.1.dist-info/METADATA
pytest_profiling-1.8.1.dist-info/WHEEL
pytest_profiling-1.8.1.dist-info/entry_points.txt
pytest_profiling-1.8.1.dist-info/top_level.txt
pytest_profiling-1.8.1.dist-info/RECORD
